{
  "id": 41946,
  "title": "élDLIVE 宇宙警探",
  "category": [
    "科幻",
    "冒險"
  ],
  "premiere": [
    2017,
    1,
    8
  ],
  "ep": 12,
  "author": "天野明",
  "website": "http://eldlive.tv/",
  "description": "中學生九之瀨宙太從小就聽得見別人聽不見的「聲音」，更因為與「聲音」對話，被當成喜歡自言自語的怪咖。然而有一天，他卻被奇怪的小不點帶到了太空船中，並被挖腳成為維護宇宙治安的宇宙警察 élDLIVE！為了不想在可愛的同學（也是宇宙警察！）其方美鈴面前丟臉，宙太答應接受試驗，想不到他必須逮捕的卻是強度超乎尋常地球人的外星罪犯。就在千鈞一髮之際，那「聲音」居然實體化了……？",
  "image": "https://myself-bbs.com/data/attachment/forum/201701/09/112914tfct9q5rjsrztltq.jpg",
  "episodes": [
    "第 01 話",
    "第 02 話",
    "第 03 話",
    "第 04 話",
    "第 05 話",
    "第 06 話",
    "第 07 話",
    "第 08 話",
    "第 09 話",
    "第 10 話",
    "第 11 話",
    "第 12 話"
  ]
}