{"id":41962,"title":"人渣的本願","category":["戀愛","校園"],"premiere":[2017,1,12],"ep":12,"author":"橫槍メンゴ","website":"http://kuzunohonkai.com/","description":"本作描述一直受到周遭同學艷羨目光的花火和麥，是一對品行端正的帥哥正妹情侶。兩人看似是一對理想的男女朋友，但其實他們共享著一個無法告人的 “某個祕密”。","image":"https://myself-bbs.com/data/attachment/forum/201701/12/0031595s888cacc5y650lq.jpg","episodes":{"第 01 話 請實現願望":["41962","001"],"第 02 話 我需要那份溫度":["41962","002"],"第 03 話 告訴我那份愛 並非…":["41962","003"],"第 04 話 Bad Apple":["41962","004"],"第 05 話 DESTRUCTION …":["41962","005"],"第 06 話 歡迎來到X次元":["41962","006"],"第 07 話 許多的愛":["41962","007"],"第 08 話 Sweet Refrain":["41962","008"],"第 09 話 beauiful swimmer":["41962","009"],"第 10 話 空洞的易碎品":["41962","010"],"第 11 話 溫柔的神明":["41962","011"],"第 12 話 2人的故事":["41962","012"]}}