{
  "id": 42124,
  "title": "黃金拼圖 Pretty Days",
  "category": [
    "搞笑",
    "百合"
  ],
  "premiere": [
    2016,
    11,
    12
  ],
  "ep": 1,
  "author": "原悠衣",
  "website": "http://www.kinmosa.com/",
  "description": "『大宮忍』是個１５歲的女孩，有著黑色的雙瞳、白皙的肌膚配上烏羽色的秀髮，外表看上去純和風的她其實曾經是英國寄宿家庭中的一份子。回國之後依舊對國外朝思暮想的她，升上高中後某日收到了一封來自外國的信件。信件寄件人居然是當時忍在英國認識的少女，也就房東家的女兒『艾莉絲』。「小忍，這次輪到我去日本住了！」。在信中表示這次換『艾莉絲』要來日本留學。席捲愛麗絲與小忍一行人的日英美少女東西合併喜劇、即將開始！！",
  "image": "https://myself-bbs.com/data/attachment/forum/201703/03/213139l9fwwmw5b5yhmyhw.jpg",
  "episodes": {}
}