{"id":42254,"title":"機甲少女／骨裝機娘／Frame Arms Girl","category":["科幻","機戰"],"premiere":[2017,4,3],"ep":12,"author":"壽屋","website":"http://www.fagirl.com/","description":"故事描述，女主角「源内あお」在某天早上，收到了一個神祕包裹。包裹裡面有著被稱為「Frame Arms Girl」的小型機器人「轟雷」，但轟雷不僅僅只是 Frame Arms Girl，而是有著自我人格的最新試作機。將藉由戰鬥資料學習感情的轟雷、以及對於 Frame Arms Girl 相關知識完全是 0 的源内あお，兩人奇妙的日常生活就此展開。","image":"https://myself-bbs.com/data/attachment/forum/201903/18/1700543xt5i7v7yxsc7xc7.jpg","episodes":{"第 01 話":"play/42254/001","第 02 話":"play/42254/002","第 03 話":"play/42254/003","第 04 話":"play/42254/004","第 05 話":"play/42254/005","第 06 話":"play/42254/006","第 07 話":"play/42254/007","第 08 話":"play/42254/008","第 09 話":"play/42254/009","第 10 話":"play/42254/010","第 11 話":"play/42254/011","第 12 話":"play/42254/012"}}