{
  "id": 43596,
  "title": "多田君不戀愛",
  "category": [
    "戀愛",
    "校園"
  ],
  "premiere": [
    2018,
    4,
    5
  ],
  "ep": 13,
  "author": "",
  "website": "http://tadakoi.tv/",
  "description": "手持相機、拍攝著盛開櫻花的「多田光良」，與剛來到日本沒多久、來自異國的少女「德蕾莎」相遇。德蕾莎來自歐洲一個名叫「萊森堡」的國家，為了留學而來到日本，但是她才剛抵達日本，就與一起來到日本的同伴走散迷了路。順理成章幫助了德蕾莎的光良，將德蕾莎帶往祖父所經營的「多田咖啡店」…",
  "image": "https://myself-bbs.com/data/attachment/forum/201804/04/212721uv0vf0xncrrv2pan.jpg",
  "episodes": [
    "第 01 話 不能放著不管吧",
    "第 02 話 算了 沒錯",
    "第 03 話 那個 挺喜歡的",
    "第 04 話 就當沒看見吧",
    "第 05 話 沒關係 不存在的",
    "第 06 話 不是雨男",
    "第 07 話 總比哭了好吧",
    "第 08 話 是雨女嗎",
    "第 09 話 現在已經沒有了",
    "第 10 話 不是真的吧",
    "第 11 話 沒什麼",
    "第 12 話 抱歉 這麼突然",
    "第 13 話 我也終生難忘"
  ]
}