{"id":43709,"title":"我的腦內戀礙選項","category":["搞笑","校園","戀愛","後宮"],"premiere":[2013,10,9],"ep":11,"author":"春日部武","website":"http://noucome.jp/","description":"私立晴光學園二年級生甘草奏是名長相俊秀的男生，但由於腦中不時會出現絕對選項之故，而被周遭的人當成變態來看待，於是過著苦難的生活。「絕對選項」是一種會突然出現腦中，不選就不消失的悲慘詛咒；通常要人被迫做變態的選擇，但若置之不理，頭就會承受超乎想像的痛苦。於是令到他整天行為舉止怪異，被列為「五黑」（指黑名單的前五位）之一。然而，在如此飽盡別人白眼的校園生活中的某天，絕對選項再次出現之際，卻讓一名美少女從天而降，同時帶來了解除絕對選項詛咒的機會……","image":"https://myself-bbs.com/data/attachment/forum/201809/01/14081813ry2l4rbjyry9yi.jpg","episodes":{"第 01 話":["43709","001"],"第 02 話":["43709","002"],"第 03 話":["43709","003"],"第 04 話":["43709","004"],"第 05 話":["43709","005"],"第 06 話":["43709","006"],"第 07 話":["43709","007"],"第 08 話":["43709","008"],"第 09 話":["43709","009"],"第 10 話":["43709","010"],"第 11 話":["43709","011"]}}