{"id":43857,"title":"日常系的異能戰鬥／日常生活中的異能戰鬥","category":["奇幻","校園","搞笑"],"premiere":[2014,10,6],"ep":12,"author":"望公太","website":"https://inou-anime.com/","description":"包含我在內的五位文藝部部員，在半年前突然都有了特別的能力，緊接著我們所面臨的是學園的超能力戰鬥！！\n\n原本以為會是這樣的，但就算有了超能力，不但沒有妄想毀滅世界的秘密機關存在，也沒有超能力戰爭，更沒有勇者與魔王，這個世界的一切還是沒有任何改變，不過即使如此，我們還是確信需要我們這超能力的戰爭將來臨。如神般的技能與戲言的日常，新‧超能力戰鬥與戀愛喜劇即將開幕！！","image":"https://myself-bbs.com/data/attachment/forum/201811/03/155656ygidypxzpjsddk7j.jpg","episodes":{"第 01 話":"play/43857/001","第 02 話":"play/43857/002","第 03 話":"play/43857/003","第 04 話":"play/43857/004","第 05 話":"play/43857/005","第 06 話":"play/43857/006","第 07 話":"play/43857/007","第 08 話":"play/43857/008","第 09 話":"play/43857/009","第 10 話":"play/43857/010","第 11 話":"play/43857/011","第 12 話":"play/43857/012"}}