{"id":43937,"title":"PUPA 蛹","category":["獵奇","奇幻"],"premiere":[2014,1,9],"ep":12,"author":"茂木清香","website":"","description":"不斷保護著重要的妹妹的哥哥－長谷川現。純粹的仰慕著哥哥的妹妹－長谷川夢。在殘酷的現實中，互相支持一起生活著的兩人，有一天，看到赤蝶的夢，被未知病毒【pupa】感染，羽化為異形的怪物，開始無差別的襲擊動物與人類。知道這件事後的現，向知道【pupa】祕密的研究者－マリア詢問抑制病毒的方法，並決定把自己的身體作為活餌獻給夢...。","image":"https://myself-bbs.com/data/attachment/forum/201812/06/213737hgu2c2b1o1hlug41.jpg","episodes":{"第 01 話":"play/43937/001","第 02 話":"play/43937/002","第 03 話":"play/43937/003","第 04 話":"play/43937/004","第 05 話":"play/43937/005","第 06 話":"play/43937/006","第 07 話":"play/43937/007","第 08 話":"play/43937/008","第 09 話":"play/43937/009","第 10 話":"play/43937/010","第 11 話":"play/43937/011","第 12 話":"play/43937/012"}}