{"id":43954,"title":"龍之界點 Dragon Crisis","category":["奇幻","冒險"],"premiere":[2011,1,10],"ep":12,"author":"城崎火也","website":"http://dragoncrisis.jp/","description":"原本只是一名平凡高中生的主角「龍司」，自從遠房表姊「英理子」從國外回來後，他的日子便產生巨變，他與英理子一同從暗黑掮客組織手中搶奪而來的竟然是龍之少女「蘿絲」。天真無邪的蘿絲對拯救自己的龍司一見鍾情，不管是吃飯還是換衣服，甚至連洗澡都如影隨形地跟在他的身邊。而原本手足無措的龍司也逐漸被這樣的蘿絲吸引，但此時暗黑組織毒牙為了奪回蘿絲再度出擊…。","image":"https://myself-bbs.com/data/attachment/forum/201812/15/1127215wqqw1w5js1vv0km.jpg","episodes":{"第 01 話 被拐走的少女":"play/43954/001","第 02 話 黑之襲擊":"play/43954/002","第 03 話 決意之契約":"play/43954/003","第 04 話 海邊的美少女":"play/43954/004","第 05 話 禁忌的覺醒":"play/43954/005","第 06 話 狼之襲擊":"play/43954/006","第 07 話 狼群們的真相":"play/43954/007","第 08 話 危險的測試":"play/43954/008","第 09 話 真實之鏡":"play/43954/009","第 10 話 成人儀式":"play/43954/010","第 11 話 Dragon Crisis":"play/43954/011","第 12 話 契約":"play/43954/012"}}