{
  "id": 43959,
  "title": "東京地震8.0／東京震級8.0",
  "category": [
    "社會寫實",
    "災難"
  ],
  "premiere": [
    2009,
    7,
    9
  ],
  "ep": 11,
  "author": "橘正紀",
  "website": "http://tokyo-m8.com/",
  "description": "《東京地震 8.0》以暑假時的台場為舞台，國中一年級的女主角「未來」陪弟弟「悠貴」去看機器人展覽，處於叛逆期的未來，正在腦中想著「為什麼每天發生的盡是一些討人厭的事情、這個世界要是能夠毀滅就好了」的瞬間，地面忽然劇烈的搖晃起來。這劇烈的晃動正是日本史上最大的芮氏震級 8.0 大地震，在巨大的地震中連東京鐵塔也都倒塌，一瞬間風雲變色的東京，未來於是牽起了弟弟悠貴的手，想盡辦法地想要回到位於世田谷的家中。",
  "image": "https://myself-bbs.com/data/attachment/forum/201812/17/2210359gwc9iitogtuc36l.jpg",
  "episodes": {
    "第 01 話 台場、沉沒": [
      "43959",
      "001"
    ],
    "第 02 話 毀壞的、世界": [
      "43959",
      "002"
    ],
    "第 03 話 燃燒的、橋": [
      "43959",
      "003"
    ],
    "第 04 話 三個人的、約定": [
      "43959",
      "004"
    ],
    "第 05 話 慟哭的、學舍": [
      "43959",
      "005"
    ],
    "第 06 話 捨棄的、選擇": [
      "43959",
      "006"
    ],
    "第 07 話 夏日黃昏": [
      "43959",
      "007"
    ],
    "第 08 話 純白的早晨": [
      "43959",
      "008"
    ],
    "第 09 話 今天、再見": [
      "43959",
      "009"
    ],
    "第 10 話 姐姐，其實我": [
      "43959",
      "010"
    ],
    "第 11 話 給悠貴…": [
      "43959",
      "011"
    ]
  }
}