{
  "id": 43983,
  "title": "空戰魔導士候補生的教官",
  "category": [
    "奇幻",
    "冒險",
    "校園",
    "後宮"
  ],
  "premiere": [
    2015,
    7,
    8
  ],
  "ep": 13,
  "author": "諸星悠",
  "website": "http://ku-sen.jp",
  "description": "這是一個被魔甲蟲奪走了大地、人類居住在天空的浮遊都市的世界。人類之中出現了身懷魔力並能與魔甲蟲對抗的魔導士——空戰魔導士。就讀於空戰魔導士育成機構的學園浮遊都市「霧槍」的彼方·英司，是被稱為「黑之劍聖」的S128特務小隊王牌。但現在則被蔑稱為「特務小隊的叛徒」而被人厭惡著.......\n\n某天，英司被任命為連戰連敗的E601小隊的教官，等待著奏多的卻是三名問題少女!?叛徒和吊車尾少女們的戰鬥就此開始。",
  "image": "https://myself-bbs.com/data/attachment/forum/201903/27/162611zwwqhxkn0z4oqfkz.jpg",
  "episodes": {
    "第 01 話 E601小隊": [
      "43983",
      "001"
    ],
    "第 02 話 最強的叛徒": [
      "43983",
      "002"
    ],
    "第 03 話 最弱所帶來的可能性": [
      "43983",
      "003"
    ],
    "第 04 話 不願忘記的過去": [
      "43983",
      "004"
    ],
    "第 05 話 勝利的鑰匙是": [
      "43983",
      "005"
    ],
    "第 06 話 被奪去的天空": [
      "43983",
      "006"
    ],
    "第 07 話 密斯特崗錦標賽": [
      "43983",
      "007"
    ],
    "第 08 話 超越等級": [
      "43983",
      "008"
    ],
    "第 09 話 必勝的方程式": [
      "43983",
      "009"
    ],
    "第 10 話 從零生出的可能性": [
      "43983",
      "010"
    ],
    "第 11 話 決勝戰，然後…": [
      "43983",
      "011"
    ],
    "第 12 話 空戰魔導士候補生…": [
      "43983",
      "012"
    ],
    "第 13 話 OVA": [
      "43983",
      "013"
    ]
  }
}