{
  "id": 44092,
  "title": "草莓棉花糖",
  "category": [
    "搞笑",
    "校園"
  ],
  "premiere": [
    2005,
    7,
    14
  ],
  "ep": 17,
  "author": "ばらスィー",
  "website": "http://www.tbs.co.jp/",
  "description": "伸惠是短期大學的女大學生，妹妹千佳是普通的小學生。但這平凡的日子卻總是充滿麻煩，問題就在於千佳的同班同學，鄰居美羽是個不折不扣的麻煩制造大王。經常從窗戶跳入千佳房間的美羽，儼然成了這個家的一員。\n\n千佳的好友茉莉是一個膽小又可愛的女孩，一天，她的班上轉來一位名叫安娜的外國女生。實際上，安娜是一個內心完全日化的女孩，而這個秘密被茉莉不小心發現了，五位女孩最終聚集在了同一個屋檐下，冷笑話不斷的同時，美羽的搞怪又讓人哭笑不得，歡樂愜意的生活喜劇就此拉開序幕。",
  "image": "https://myself-bbs.com/data/attachment/forum/201903/22/200625aa1h9h1udd93hmd4.jpg",
  "episodes": [
    "第 01 話 生日",
    "第 02 話 安娜",
    "第 03 話 拜訪",
    "第 04 話 打工",
    "第 05 話 一起睡",
    "第 06 話 正夏日",
    "第 07 話 海水浴",
    "第 08 話 祭典",
    "第 09 話 成長顛峰期",
    "第 10 話 花",
    "第 11 話 初雪",
    "第 12 話 禮物",
    "OVA 01 景色",
    "OVA 02 無論何時",
    "OVA 03 每一天",
    "OVA 04 你好",
    "OVA 05 明天再見"
  ]
}