{
  "id": 44141,
  "title": "深淵傳說 Tales of the Abyss",
  "category": [
    "奇幻",
    "冒險"
  ],
  "premiere": [
    2008,
    10,
    3
  ],
  "ep": 26,
  "author": "南夢宮萬代",
  "website": "",
  "description": "故事描述 2000 年前，在行星奧爾多蘭特上的人們，發現了存有「星之記憶﹝奧爾多蘭特行星從誕生至毀滅的紀錄，換句話說就是過去以至於未來的歷史紀錄﹞」的第七音素，隨著星之記憶的發現，爆發了一連串的戰亂，這場長久的戰亂不僅重創了奧爾多蘭特的居民，就連奧爾多蘭特都一片荒寂，劇烈的地殼變動使得大地產生了有毒的瘴氣。最後人類遵循能解讀星之記憶的天才音律士（操作音素之力者）尤里雅‧裘耶的預言，而避免了滅亡的命運，並將瘴氣深深的封閉於地底，就這樣過了千年之久。時間來到現代，奧爾多蘭特由兩大國的勢力所瓜分，保持著恐怖均衡的狀態，而尤里雅偉大的事蹟雀反被以護衛尤里雅教誨為宗旨的羅蕾萊（Loreilei）教團的「預言（Score）」利用來控制人心……",
  "image": "https://myself-bbs.com/data/attachment/forum/201905/08/124402bdhmhlhnirv5rdlk.jpg",
  "episodes": {
    "第 01 話": [
      "44141",
      "001"
    ],
    "第 02 話": [
      "44141",
      "002"
    ],
    "第 03 話": [
      "44141",
      "003"
    ],
    "第 04 話": [
      "44141",
      "004"
    ],
    "第 05 話": [
      "44141",
      "005"
    ],
    "第 06 話": [
      "44141",
      "006"
    ],
    "第 07 話": [
      "44141",
      "007"
    ],
    "第 08 話": [
      "44141",
      "008"
    ],
    "第 09 話": [
      "44141",
      "009"
    ],
    "第 10 話": [
      "44141",
      "010"
    ],
    "第 11 話": [
      "44141",
      "011"
    ],
    "第 12 話": [
      "44141",
      "012"
    ],
    "第 13 話": [
      "44141",
      "013"
    ],
    "第 14 話": [
      "44141",
      "014"
    ],
    "第 15 話": [
      "44141",
      "015"
    ],
    "第 16 話": [
      "44141",
      "016"
    ],
    "第 17 話": [
      "44141",
      "017"
    ],
    "第 18 話": [
      "44141",
      "018"
    ],
    "第 19 話": [
      "44141",
      "019"
    ],
    "第 20 話": [
      "44141",
      "020"
    ],
    "第 21 話": [
      "44141",
      "021"
    ],
    "第 22 話": [
      "44141",
      "022"
    ],
    "第 23 話": [
      "44141",
      "023"
    ],
    "第 24 話": [
      "44141",
      "024"
    ],
    "第 25 話": [
      "44141",
      "025"
    ],
    "第 26 話": [
      "44141",
      "026"
    ]
  }
}