{"id":44283,"title":"DAYS","category":["運動","校園","競技"],"premiere":[2016,7,2],"ep":24,"author":"安田剛士","website":"http://days-project.jp/","description":"柄本盡司是個沒有任何優點，沒有任何特技的少年。有一天在因緣巧合下認識了古怪的少年風間陣，也在陣的邀請下參加了五人制足球的比賽，想不到這就此發掘了阿盡最大的特色。明知自己是個門外漢，盡司仍勇敢地參加了足球名校聖蹟高中的足球社，而他的熱血表現也逐漸改變了陣以及所有的隊友。震撼高中足球的奇蹟故事開始了！","image":"https://myself-bbs.com/data/attachment/forum/201909/19/123633zz1kbiwfl3ij20l1.jpg","episodes":{"第 01 話":["44283","001"],"第 02 話":["44283","002"],"第 03 話":["44283","003"],"第 04 話":["44283","004"],"第 05 話":["44283","005"],"第 06 話":["44283","006"],"第 07 話":["44283","007"],"第 08 話":["44283","008"],"第 09 話":["44283","009"],"第 10 話":["44283","010"],"第 11 話":["44283","011"],"第 12 話":["44283","012"],"第 13 話":["44283","013"],"第 14 話":["44283","014"],"第 15 話":["44283","015"],"第 16 話":["44283","016"],"第 17 話":["44283","017"],"第 18 話":["44283","018"],"第 19 話":["44283","019"],"第 20 話":["44283","020"],"第 21 話":["44283","021"],"第 22 話":["44283","022"],"第 23 話":["44283","023"],"第 24 話":["44283","024"],"OAD 01":["44283","025"],"OAD 02":["44283","026"],"OAD 03 東院學園戰 前篇":["44283","028"],"OAD 04 東院學園戰 中篇":["44283","029"],"OAD 05 東院學園戰 後篇":["44283","027"]}}