{"id":44380,"title":"血界戰線／幻界戰線","category":["科幻","冒險"],"premiere":[2015,4,4],"ep":12,"author":"內藤泰弘","website":"http://kekkaisensen.com/","description":"故事敘述紐約崩壞後，一夜之間便架構成『赫爾沙雷姆茲‧羅特』這個城市。 在連繫著異世界與現世界的這個魔都裡，有個為了保持世界的平衡而在暗地裡非常活躍的組織──秘密結社萊布拉 ！！ 少年雷歐在一連串的巧合下，加入萊布拉，他身上所隱藏的秘密將會對萊布拉造成什麼影響……！？","image":"https://myself-bbs.com/data/attachment/forum/202001/18/134218thtkj1iqb5zhkhta.jpg","episodes":{"第 01 話 魔封街結社":"play/44380/001","第 02 話 追逐幻之幽靈車輛":"play/44380/002","第 03 話 世界與世界的遊戲":"play/44380/003","第 04 話 Blood line fever":"play/44380/004","第 05 話 震擊之血槌":"play/44380/005","第 06 話 Don't forget to…":"play/44380/006","第 07 話 拳客的伊甸園":"play/44380/007","第 08 話 Z最長的一天(前篇)":"play/44380/008","第 09 話 Z最長的一天(後篇)":"play/44380/009","第 10 話 Run!Lunch!!…":"play/44380/010","第 11 話 Paint It Black":"play/44380/011","第 12 話 Hello,world!":"play/44380/012"}}