{"id":44437,"title":"幻想玩偶 Fantasista Doll","category":["奇幻","冒險"],"premiere":[2013,7,6],"ep":12,"author":"ファンタジスタドール","website":"http://fantasistadoll.com/","description":"“我們是幻想玩偶，能實現女孩子們的願望”，那是一班少女們希望實現的原動力。就讀於私立聖悠學館中學部的中學生鵜野渦芽，偶然入手名為「幻想玩偶」的卡牌，從中召喚出五位少女玩偶，並成為她們的主人，自此肩負起拯救世界的責任，展開戰鬥。","image":"https://myself-bbs.com/data/attachment/forum/202007/08/110648m9mfmsp9161ahhln.jpg","episodes":{"第 01 話":"play/44437/001","第 02 話":"play/44437/002","第 03 話":"AgAD2QsAAqywWVc","第 04 話":"play/44437/004","第 05 話":"AgAD6gkAAqywWVc","第 06 話":"play/44437/006","第 07 話":"play/44437/007","第 08 話":"AgAD7gkAAqywWVc","第 09 話":"play/44437/009","第 10 話":"play/44437/010","第 11 話":"play/44437/011","第 12 話":"AgAD8wkAAqywWVc"}}