{
  "id": 44565,
  "title": "空中殺手",
  "category": [
    "科幻"
  ],
  "premiere": [
    2008,
    8,
    2
  ],
  "ep": 1,
  "author": "森博嗣",
  "website": "",
  "description": "函南優一是戰爭承包公司「羅斯托克社」所屬的戰鬥機飛行員，被派往前線基地“兔離州”的他，對於到那裡生活之前的記憶毫無印象，對他來說，空中作戰就是他的全部。某天，他與基地的女司令官草薙水素相遇，優一雖然聽聞水素許多不好的傳言，但他仍然深深地被她所吸引。而另一方面，基地的戰況也日趨激烈，優一的許多夥伴紛紛被擊落戰死，然而在不斷遞補進來的飛行員中，優一赫然發現，其中有一位竟然與之前已經戰死的夥伴有著相同的折報習慣。這……究竟意味著什麼？優一想起之前素子所告訴他的話: “殺了我，如何？要不然，我們永遠都只能是這個樣子了。”不久，優一的記憶恢復了，當他終於明白了一切的瞬間，他馬上下定決心要奮起迎戰反抗命運…",
  "image": "https://myself-bbs.com/data/attachment/forum/202009/20/1031194kh2imhko00ki283.jpg",
  "episodes": [
    "第 01 話"
  ]
}