{"id":44952,"title":"BASILISK 櫻花忍法帖","category":["動作","冒險","奇幻"],"premiere":[2018,1,8],"ep":24,"author":"山田正紀","website":"","description":"故事發生在《甲賀忍法帖》10年後的寬永三年。為天下之權鬥爭的歷史背後、忍者集團甲賀與伊賀為了自己所效力的主人展開了一連串忍法殺戮戰爭，並在最終迎來了雙方全滅的結局──這場鬥爭結束十年之後，寬永三年，甲賀五寶連所管束、擁有茅眼術操縱能力的少年「甲賀五郎」，與伊賀五花撰中能使用盾眼術的少女「伊賀響」終於相遇，他們以操縱超人之力、號稱成尋眾的神秘集團為目標，被卷入了一場一想不到的戰爭之中。","image":"https://myself-bbs.com/data/attachment/forum/202302/21/180420v3x77bgnxxxkxj6t.jpg","episodes":{"第 01 話 櫻花綻放":"AgADBQoAAmdfoFc","第 02 話 五寶連 上陣":"AgADBgoAAmdfoFc","第 03 話 甲賀凋零":"AgADBwoAAmdfoFc","第 04 話 成尋眾現身":"AgADCAoAAmdfoFc","第 05 話 櫻花狂奔":"AgADCQoAAmdfoFc","第 06 話 兇雲胎動":"AgADCgoAAmdfoFc","第 07 話 忠長變卦":"AgADCwoAAmdfoFc","第 08 話 成尋再來":"AgADDQoAAmdfoFc","第 09 話 蝴蝶曼舞":"AgADDgoAAmdfoFc","第 10 話 羽衣見修羅":"AgADDwoAAmdfoFc","第 11 話 如犀角獨行":"AgADEAoAAmdfoFc","第 12 話 松籟陣陣":"AgADEQoAAmdfoFc","第 13 話 現 凝視奈落之夢":"AgADFAoAAmdfoFc","第 14 話 討滅叢雲":"AgADFQoAAmdfoFc","第 15 話 盾眼受騙":"AgADFwoAAmdfoFc","第 16 話 巨城鳴動":"AgADGAoAAmdfoFc","第 17 話 全員 聚於修羅":"AgADGQoAAmdfoFc","第 18 話 櫻花凋零":"AgADGgoAAmdfoFc","第 19 話 百目 窺見宿命":"AgAD_ggAAmdfqFc","第 20 話 面影失散":"AgAD_wgAAmdfqFc","第 21 話 面影失散":"AgAECQACZ1-oVw","第 22 話 魔 死而復生":"AgADAQkAAmdfqFc","第 23 話 櫻花亂舞":"AgADAgkAAmdfqFc","第 24 話 櫻花重綻":"AgADAwkAAmdfqFc"}}