{
  "id": 45137,
  "title": "GRANBELM 滿月之戰",
  "category": [
    "奇幻",
    "冒險"
  ],
  "premiere": [
    2019,
    7,
    5
  ],
  "ep": 13,
  "author": "ProjectGRANBELM",
  "website": "http://granbelm.com/",
  "description": "魔力從世界消失已經有將近1000年的時間，人們也完全忘記了過去的魔法，而在這樣的世界生活的元氣高中生小日向滿月雖然積極的度過每一天，但是心中卻隱隱有著一份不安，既不擅長運動也不擅長學習的她在苦惱什麼是只有自己才能夠做到的事情，而在一個月圓之夜，小日向滿月遇到了另一位名字中有「月」的少女 新月埃內斯塔深海，而兩人的這場相遇轉動了命運的齒輪，得知了世界秘密的少女要做出自己的選擇。",
  "image": "https://myself-bbs.com/data/attachment/forum/201907/07/0349231vzx22jhx7j1v2iv.jpg",
  "episodes": {
    "第 01 話 世界上唯一的魔術師": [
      "45137",
      "001"
    ],
    "第 02 話 為了我能存在於此": [
      "45137",
      "002"
    ],
    "第 03 話 鐘聲敲響在滿月": [
      "45137",
      "003"
    ],
    "第 04 話 風水師林芬芬": [
      "45137",
      "004"
    ],
    "第 05 話 小小少女的小小心願": [
      "45137",
      "005"
    ],
    "第 06 話 魔石": [
      "45137",
      "006"
    ],
    "第 07 話 怨婦": [
      "45137",
      "007"
    ],
    "第 08 話 所謂成為魔術師": [
      "45137",
      "008"
    ],
    "第 09 話 夜曲，浸染一切": [
      "45137",
      "009"
    ],
    "第 10 話 思緒萬千的人偶": [
      "45137",
      "010"
    ],
    "第 11 話 就算告別無法傳達": [
      "45137",
      "011"
    ],
    "第 12 話 魔力結界": [
      "45137",
      "012"
    ],
    "第 13 話 為了世界唯一的兩人": [
      "45137",
      "013"
    ]
  }
}