{"id":47237,"title":"關於我轉生變成史萊姆這檔事 轉生史萊姆日記","category":["搞笑"],"premiere":[2021,4,6],"ep":12,"author":"伏瀨","website":"https://www.ten-sura.com/","description":"由於得到了珍貴的紙，我決定將自己至今為止的經歷以日記的形式記錄下來。日記標題的話……就寫《我轉生後變成了史萊姆》。自那之後我的冒險就開始了——冒險要寫的東西也長了吧？\n\n描述了愛開玩笑且幽默的利姆魯與特恩佩斯特的同伴們之間的日常故事的「史萊姆生活系」轉生物語，現在開幕！","image":"https://myself-bbs.com/data/attachment/forum/202104/07/101350yyyyaoim00k46iwp.jpg","episodes":{"第 01 話":["47237","001"],"第 02 話":["47237","002"],"第 03 話":["47237","003"],"第 04 話":["47237","004"],"第 05 話":["47237","005"],"第 06 話":["47237","006"],"第 07 話":["47237","007"],"第 08 話":["47237","008"],"第 09 話":["47237","009"],"第 10 話":["47237","010"],"第 11 話":["47237","011"],"第 12 話":["47237","012"]}}