{"id":49580,"title":"寵物小精靈 / 寶可夢 地平線 莉可與羅伊的啟程","category":["冒險","奇幻"],"premiere":[2023,4,14],"ep":0,"author":"田尻智","website":"https://www.tv-tokyo.co.jp/anime/pocketmonster2023/","description":"2022年12月16日，在播出《寵物小精靈 旅途》最終話後，宣佈製作全新《寵物小精靈系列》動畫，但不同於過去以小智和皮卡丘作為主角，而是採用新主角莉可和羅伊。","image":"https://myself-bbs.com/data/attachment/forum/202304/15/19592703j3z0dsj44ippkp.jpg","episodes":{"第 01 話":"AgADwAkAAoEa2FU","第 02 話":"AgADwgkAAoEa2FU","第 03 話":"AgAD7wcAAviYIFY","第 04 話":"AgAD9wkAAv-heVY","第 05 話":"AgADuwoAAlNhwVY"}}