{"id":49754,"title":"其實，我乃最強？","category":["奇幻","冒險","搞笑"],"premiere":[2023,7,1],"ep":12,"author":"澄守彩","website":"https://jitsuhaoresaikyo-anime.com/","description":"家裡蹲的我，某日轉生到異世界成為了一國王子，但由於魔力值低下……出生第一天就要被殺掉了！？就在我被拋棄在遠方森林之中時，遭遇了一隻巨大魔獸……為求自保，我嘗試發動魔法進行反擊，但魔獸不知為何變成了美少女，還成為了我的從者。稀里糊塗成為「魔王」的我，開啟了左擁右抱的新生活！","image":"https://myself-bbs.com/data/attachment/forum/202307/28/202706d66dmlmkzdmdlmee.jpg","episodes":{"第 01 話":"AgADSgsAAnegCVU","第 02 話":"AgAD-ggAAsU4UVU","第 03 話":"AgAD7AgAAnM4mFU","第 04 話":"AgADmAoAA5HhVQ","第 05 話":"AgADEwwAAlBpKVY"}}